django_messagegroups-0.4.5.dist-info/DESCRIPTION.rst
django_messagegroups-0.4.5.dist-info/METADATA
django_messagegroups-0.4.5.dist-info/RECORD
django_messagegroups-0.4.5.dist-info/WHEEL
django_messagegroups-0.4.5.dist-info/metadata.json
django_messagegroups-0.4.5.dist-info/top_level.txt
messagegroups/__init__.py
messagegroups/tests.py
messagegroups/templates/messagegroups.html
messagegroups/templatetags/__init__.py
messagegroups/templatetags/messagegroups.py
